{
  "id": 527,
  "name": "woobat",
  "types": [
    {
      "slot": 1,
      "type": {
        "name": "psychic",
        "url": "https://pokeapi.co/api/v2/type/14/"
      }
    },
    {
      "slot": 2,
      "type": {
        "name": "flying",
        "url": "https://pokeapi.co/api/v2/type/3/"
      }
    }
  ],
  "flavor_text_entries": [
    "Suction from its nostrils enables it to stick to cave walls during sleep. It leaves a heart-shaped mark behind.",
    "The heart-shaped mark left on a body after a Woobat has been attached to it is said to bring good fortune.",
    "It emits ultrasonic waves as it flutters about, searching for its prey\u2014bug Pok\u00e9mon.",
    "Its habitat is dark forests and caves. It emits ultrasonic waves from its nose to learn about its surroundings.",
    "While inside a cave, if you look up and see lots of heart-shaped marks lining the walls, it\u2019s evidence that Woobat live there."
  ],
  "genera": [
    {
      "genus": "Bat Pok\u00e9mon",
      "language": {
        "name": "en",
        "url": "https://pokeapi.co/api/v2/language/9/"
      }
    }
  ]
}