{
  "id": 648,
  "name": "meloetta",
  "types": [
    {
      "slot": 1,
      "type": {
        "name": "normal",
        "url": "https://pokeapi.co/api/v2/type/1/"
      }
    },
    {
      "slot": 2,
      "type": {
        "name": "psychic",
        "url": "https://pokeapi.co/api/v2/type/14/"
      }
    }
  ],
  "flavor_text_entries": [
    "The melodies sung by Meloetta have the power to make Pok\u00e9mon that hear them happy or sad.",
    "Many famous songs have been inspired by the melodies that Meloetta plays.",
    "Its melodies are sung with a special vocalization method that can control the feelings of those who hear it."
  ],
  "genera": [
    {
      "genus": "Melody Pok\u00e9mon",
      "language": {
        "name": "en",
        "url": "https://pokeapi.co/api/v2/language/9/"
      }
    }
  ]
}