{
  "id": 944,
  "name": "shroodle",
  "types": [
    {
      "slot": 1,
      "type": {
        "name": "poison",
        "url": "https://pokeapi.co/api/v2/type/4/"
      }
    },
    {
      "slot": 2,
      "type": {
        "name": "normal",
        "url": "https://pokeapi.co/api/v2/type/1/"
      }
    }
  ],
  "flavor_text_entries": [
    "Though usually a mellow Pok\u00e9mon, it will sink its sharp, poison-soaked front teeth into any that anger it, causing paralysis in the object of its ire.",
    "To keep enemies away from its territory, it paints markings around its nest using a poisonous liquid that has an acrid odor."
  ],
  "genera": [
    {
      "genus": "Toxic Mouse Pok\u00e9mon",
      "language": {
        "name": "en",
        "url": "https://pokeapi.co/api/v2/language/9/"
      }
    }
  ]
}