{
  "id": 954,
  "name": "rabsca",
  "types": [
    {
      "slot": 1,
      "type": {
        "name": "bug",
        "url": "https://pokeapi.co/api/v2/type/7/"
      }
    },
    {
      "slot": 2,
      "type": {
        "name": "psychic",
        "url": "https://pokeapi.co/api/v2/type/14/"
      }
    }
  ],
  "flavor_text_entries": [
    "The body that supports the ball barely moves. Therefore, it is thought that the true body of this Pok\u00e9mon is actually inside the ball.",
    "An infant sleeps inside the ball. Rabsca rolls the ball soothingly with its legs to ensure the infant sleeps comfortably."
  ],
  "genera": [
    {
      "genus": "Rolling Pok\u00e9mon",
      "language": {
        "name": "en",
        "url": "https://pokeapi.co/api/v2/language/9/"
      }
    }
  ]
}